bibupdate/__init__.py
bibupdate-1.2.dist-info/DESCRIPTION.rst
bibupdate-1.2.dist-info/entry_points.txt
bibupdate-1.2.dist-info/METADATA
bibupdate-1.2.dist-info/metadata.json
bibupdate-1.2.dist-info/RECORD
bibupdate-1.2.dist-info/top_level.txt
bibupdate-1.2.dist-info/WHEEL
update_bib/__init__.py
