Metadata-Version: 2.0
Name: bibupdate
Version: 1.2
Summary: ('Automatically update the entries of a bibtex file using mrlookup/MathSciNet',)
Home-page: ('https://bitbucket.org/AndrewsBucket/bibupdate',)
Author: ('Andrew Mathas',)
Author-email: ('andrew.mathas@gmail.com',)
License: GNU General Public License, Version 3, 29 June 2007
Keywords: bibtex, mrlookup, MathSciNet, latex
Platform: UNKNOWN
Classifier: Development Status :: 5 - Production/Stable
Classifier: Environment :: Console
Classifier: Intended Audience :: Science/Research
Classifier: License :: OSI Approved :: GNU General Public License v3 or later (GPLv3+)
Classifier: Natural Language :: English
Classifier: Programming Language :: Python :: 2.7
Classifier: Topic :: Text Processing :: Markup :: LaTeX
Classifier: Topic :: Utilities
Requires-Dist: fuzzywuzzy (>=0.2)
